pystixview/__init__.py
pystixview/_version.py
pystixview/icons/LICENSE
pystixview/icons/custom/noback-dark.png
pystixview/icons/custom/noback-flat.png
pystixview/icons/custom/round-flat.png
pystixview/icons/custom/square-dark.png
pystixview/icons/custom/square-flat.png
pystixview/icons/custom/square-lite.png
pystixview/icons/generic/tlp-amber-noback-dark.png
pystixview/icons/generic/tlp-amber-noback-flat.png
pystixview/icons/generic/tlp-amber-round-flat.png
pystixview/icons/generic/tlp-amber-square-dark.png
pystixview/icons/generic/tlp-amber-square-flat.png
pystixview/icons/generic/tlp-amber-square-lite.png
pystixview/icons/generic/tlp-green-noback-dark.png
pystixview/icons/generic/tlp-green-noback-flat.png
pystixview/icons/generic/tlp-green-round-flat.png
pystixview/icons/generic/tlp-green-square-dark.png
pystixview/icons/generic/tlp-green-square-flat.png
pystixview/icons/generic/tlp-green-square-lite.png
pystixview/icons/generic/tlp-red-noback-dark.png
pystixview/icons/generic/tlp-red-noback-flat.png
pystixview/icons/generic/tlp-red-round-flat.png
pystixview/icons/generic/tlp-red-square-dark.png
pystixview/icons/generic/tlp-red-square-flat.png
pystixview/icons/generic/tlp-red-square-lite.png
pystixview/icons/generic/tlp-restricted-noback-dark.png
pystixview/icons/generic/tlp-restricted-noback-flat.png
pystixview/icons/generic/tlp-restricted-round-flat.png
pystixview/icons/generic/tlp-restricted-square-dark.png
pystixview/icons/generic/tlp-restricted-square-flat.png
pystixview/icons/generic/tlp-restricted-square-lite.png
pystixview/icons/generic/tlp-white-noback-dark.png
pystixview/icons/generic/tlp-white-noback-flat.png
pystixview/icons/generic/tlp-white-round-flat.png
pystixview/icons/generic/tlp-white-square-dark.png
pystixview/icons/generic/tlp-white-square-flat.png
pystixview/icons/generic/tlp-white-square-lite.png
pystixview/icons/observable/autonomous-system/noback-dark.png
pystixview/icons/observable/autonomous-system/noback-flat.png
pystixview-0.1.7.dist-info/LICENSE
pystixview-0.1.7.dist-info/METADATA
pystixview-0.1.7.dist-info/WHEEL
pystixview-0.1.7.dist-info/RECORD
