Metadata-Version: 2.3
Name: pystixview
Version: 0.1.7
Summary: A Python library to create and display STIX2 graphs
License: BSD 3-Clause
Author: Vincenzo Caputo
Author-email: caputo.vincenzo@protonmail.com
Requires-Python: >=3.10,<4.0
Classifier: License :: Other/Proprietary License
Classifier: Operating System :: OS Independent
Classifier: Programming Language :: Python :: 3
Classifier: Programming Language :: Python :: 3.10
Classifier: Programming Language :: Python :: 3.11
Classifier: Programming Language :: Python :: 3.12
Classifier: Programming Language :: Python :: 3.13
Requires-Dist: beautifulsoup4 (>=4.12.3,<5.0.0)
Requires-Dist: ipython (>=8.23.0,<9.0.0)
Requires-Dist: pyvis (>=0.3.2,<0.4.0)
Requires-Dist: stix2 (>=3.0.1,<4.0.0)
Project-URL: Documentation, https://pystixview.readthedocs.io
Project-URL: Homepage, https://github.com/vincenzocaputo/PySTIXView
Project-URL: Issues, https://github.com/vincenzocaputo/PySTIXView/issues
